dlproject/__init__.py
dlproject/experiments.py
dlproject/logging.py
dlproject/utils.py
dlproject/datasets/__init__.py
dlproject/datasets/mnist.py
dlproject/models/__init__.py
dlproject/models/classifier.py
tests/__init__.py
tests/test_mnist.py
dlproject-0.1.1.dist-info/LICENSE
dlproject-0.1.1.dist-info/METADATA
dlproject-0.1.1.dist-info/WHEEL
dlproject-0.1.1.dist-info/top_level.txt
dlproject-0.1.1.dist-info/RECORD
