Metadata-Version: 2.1
Name: dlproject
Version: 0.1.1
Summary: The opinionated deep learning template.
Home-page: https://github.com/benjamindkilleen/dlproject
Author: Benjamin D. Killeen
Author-email: killeen@jhu.edu
License: UNKNOWN
Platform: UNKNOWN
License-File: LICENSE
Requires-Dist: torch
Requires-Dist: torchvision
Requires-Dist: pytorch-lightning
Requires-Dist: hydra-core
Requires-Dist: omegaconf
Requires-Dist: hydra-colorlog
Requires-Dist: numpy
